admin_searchable_dropdown/__init__.py
admin_searchable_dropdown/apps.py
admin_searchable_dropdown/filters.py
admin_searchable_dropdown/views.py
admin_searchable_dropdown/static/django-admin-autocomplete-filter/css/autocomplete-fix.css
admin_searchable_dropdown/static/django-admin-autocomplete-filter/js/autocomplete_filter_qs.js
admin_searchable_dropdown/static/django-admin-searchable-dropdown/css/autocomplete-fix.css
admin_searchable_dropdown/static/django-admin-searchable-dropdown/js/autocomplete_filter_qs.js
admin_searchable_dropdown/templates/django-admin-autocomplete-filter/autocomplete-filter.html
admin_searchable_dropdown/templates/django-admin-searchable-dropdown/autocomplete-filter.html
django_admin_searchable_dropdown-1.2.dist-info/LICENSE
django_admin_searchable_dropdown-1.2.dist-info/METADATA
django_admin_searchable_dropdown-1.2.dist-info/WHEEL
django_admin_searchable_dropdown-1.2.dist-info/top_level.txt
django_admin_searchable_dropdown-1.2.dist-info/RECORD
