Metadata-Version: 2.1
Name: django-admin-searchable-dropdown
Version: 1.2
Summary: A simple Django app to render list filters in dropdown format with search option
Home-page: https://github.com/whoisashish/django-admin-searchable-dropdown
Author: Ashish Yadav
Author-email: anujashish1602@gmail.com
License: UNKNOWN
Platform: UNKNOWN
Classifier: Framework :: Django
Classifier: Framework :: Django :: 2.0
Classifier: Intended Audience :: Developers
Classifier: License :: OSI Approved :: GNU Lesser General Public License v3 (LGPLv3)
Classifier: Operating System :: OS Independent
Classifier: Programming Language :: Python :: 3.5
Classifier: Programming Language :: Python :: 3.6
Classifier: Topic :: Internet :: WWW/HTTP
Classifier: Topic :: Software Development :: Libraries :: Python Modules
License-File: LICENSE
